trafficinterventions/ChangeEdges.py
trafficinterventions/ChangeLanes.py
trafficinterventions/ChangeTrips.py
trafficinterventions/EmissionJunction.py
trafficinterventions/SpeedCamera.py
trafficinterventions/StressJunction.py
trafficinterventions/__init__.py
trafficinterventions-2.0.4.dist-info/LICENSE
trafficinterventions-2.0.4.dist-info/METADATA
trafficinterventions-2.0.4.dist-info/WHEEL
trafficinterventions-2.0.4.dist-info/top_level.txt
trafficinterventions-2.0.4.dist-info/RECORD
