Metadata-Version: 2.1
Name: trafficinterventions
Version: 2.0.4
Summary: Python Package to perform simple Traffic Interventions and run traffic simulations.
Home-page: https://github.com/WSL-IIITB/Traffic-Interventions
Author: WSL, IIITB
Author-email: WSL1@iiitb.ac.in
Project-URL: Bug Tracker, https://github.com/WSL-IIITB/Traffic-Interventions/issues
Classifier: Programming Language :: Python :: 3
Classifier: License :: OSI Approved :: MIT License
Classifier: Operating System :: OS Independent
Requires-Python: >=3.6
License-File: LICENSE
